Workbook

Sheet Mode d'emploi
B1: Catalogue fournisseur — pièces détachées Autopiec
B2: Merci de compléter ce fichier afin d'intégrer vos références dans notre base de données.
B4: 1. Onglet « Fournisseur » : complétez vos coordonnées (cellules jaunes).
B5: 2. Onglet « Catalogue » : une ligne = une référence. Commencez en ligne 2, sans ligne vide intercalée.
B6: 3. Les colonnes à en-tête ORANGE et marquées * sont obligatoires ; les colonnes BLEUES sont facultatives mais recommandées.
B7: 4. Les colonnes GRISES (Remise, Contrôle) se calculent seules : ne les modifiez pas.
B8: 5. Survolez un en-tête pour afficher l'aide de la colonne. Utilisez les listes déroulantes quand elles existent.
B9: 6. Prix en euros HORS TAXES, saisis en nombre sans symbole (ex : 42,90). Le prix Autopiec doit être ≤ au prix public.
B10: 7. Avant envoi, vérifiez que la colonne « Contrôle » n'affiche que « ✔ OK » (synthèse dans l'onglet Fournisseur).
B11: 8. Ne renommez pas les onglets et ne modifiez pas l'ordre des colonnes (import automatique).
B12: 9. Renvoyez le fichier au format .xlsx, nommé : Catalogue_<NomFournisseur>_<AAAAMMJJ>.xlsx
B14: Légende des couleurs
C15: En-tête obligatoire
C16: En-tête facultatif
C17: Calcul automatique — ne pas saisir
C18: Cellule à compléter / champ obligatoire manquant
B20: Exemple de ligne correctement remplie (onglet Catalogue)
B21: Marque | C21: Référence produit | D21: Désignation | E21: Catégorie | F21: État | G21: Prix public HT | H21: Prix Autopiec HT
B22: Bosch | C22: 0 986 494 399 | D22: Jeu de 4 plaquettes de frein avant | E22: Freinage | F22: Neuf | G22: 58.9 | H22: 41.23
B23: Suite de la ligne : Qté disponible 24 · Réf. OEM 7701208177 · EAN 4047025573389 · Compatibilité Renault Clio IV 1.5 dCi 2012-2019 · TVA 20 % · Délai 2 j · Garantie 24 mois.
B24: Valeurs d'exemple fictives, données à titre d'illustration du format attendu.

Sheet Fournisseur
A1: Informations fournisseur
A3: Raison sociale *
A4: N° SIRET *
A5: N° TVA intracommunautaire
A6: Contact (nom, prénom) *
A7: E-mail *
A8: Téléphone
A9: Adresse d'expédition
A10: Conditions de paiement
A11: Franco de port (€ HT)
A12: Date de validité des prix *
A13: Date d'envoi du fichier
A16: Synthèse du catalogue (calcul automatique)
A17: Nombre de références saisies | B17: =COUNTIF(Catalogue!U2:U1001,"?*") -> 0
A18: Lignes valides | B18: =COUNTIF(Catalogue!U2:U1001,"✔*") -> 0
A19: Lignes à corriger | B19: =COUNTIF(Catalogue!U2:U1001,"⚠*") -> 0
A20: Remise moyenne accordée | B20: =IFERROR(AVERAGE(Catalogue!L2:L1001),0) -> 0
A21: Valeur du stock au prix Autopiec (€ HT) | B21: =SUMPRODUCT(N(+Catalogue!K2:K1001),N(+Catalogue!N2:N1001)) -> 0

Sheet Catalogue
A1: Marque * | B1: Référence produit * | C1: Désignation * | D1: Catégorie * | E1: État * | F1: Référence OEM / constructeur | G1: Code EAN | H1: Véhicules compatibles | I1: Unité de vente | J1: Prix public HT (€) * | K1: Prix Autopiec HT (€) * | L1: Remise (%) | M1: Taux TVA | N1: Quantité disponible * | O1: Qté minimum de commande | P1: Délai de livraison (jours ouvrés) | Q1: Poids (kg) | R1: Garantie (mois) | S1: Lien photo (URL) | T1: Commentaires | U1: Contrôle
L2: =IF(AND(ISNUMBER(J2),ISNUMBER(K2),N(J2)>0),1-K2/J2,"") | U2: =IF((LEN(A2)+LEN(B2)+LEN(C2)+LEN(D2)+LEN(E2)+LEN(F2)+LEN(G2)+LEN(H2)+LEN(I2)+LEN(J2)+LEN(K2)+LEN(M2)+LEN(N2)+LEN(O2)+LEN(P2)+LEN(Q2)+LEN(R2)+LEN(S2)+LEN(T2))=0,"",IF(OR(A2="",B2="",C2="",D2="",E2="",J2="",K2="",N2=""),"⚠ Champ obligatoire manquant",IF(AND(ISNUMBER(K2),ISNUMBER(J2),N(K2)>N(J2)),"⚠ Prix Autopiec > prix public",IF(COUNTIFS($A$2:$A$1001,A2,$B$2:$B$1001,B2)>1,"⚠ Référence en double","✔ OK"))))
L3: =IF(AND(ISNUMBER(J3),ISNUMBER(K3),N(J3)>0),1-K3/J3,"") | U3: =IF((LEN(A3)+LEN(B3)+LEN(C3)+LEN(D3)+LEN(E3)+LEN(F3)+LEN(G3)+LEN(H3)+LEN(I3)+LEN(J3)+LEN(K3)+LEN(M3)+LEN(N3)+LEN(O3)+LEN(P3)+LEN(Q3)+LEN(R3)+LEN(S3)+LEN(T3))=0,"",IF(OR(A3="",B3="",C3="",D3="",E3="",J3="",K3="",N3=""),"⚠ Champ obligatoire manquant",IF(AND(ISNUMBER(K3),ISNUMBER(J3),N(K3)>N(J3)),"⚠ Prix Autopiec > prix public",IF(COUNTIFS($A$2:$A$1001,A3,$B$2:$B$1001,B3)>1,"⚠ Référence en double","✔ OK"))))
L4: =IF(AND(ISNUMBER(J4),ISNUMBER(K4),N(J4)>0),1-K4/J4,"") | U4: =IF((LEN(A4)+LEN(B4)+LEN(C4)+LEN(D4)+LEN(E4)+LEN(F4)+LEN(G4)+LEN(H4)+LEN(I4)+LEN(J4)+LEN(K4)+LEN(M4)+LEN(N4)+LEN(O4)+LEN(P4)+LEN(Q4)+LEN(R4)+LEN(S4)+LEN(T4))=0,"",IF(OR(A4="",B4="",C4="",D4="",E4="",J4="",K4="",N4=""),"⚠ Champ obligatoire manquant",IF(AND(ISNUMBER(K4),ISNUMBER(J4),N(K4)>N(J4)),"⚠ Prix Autopiec > prix public",IF(COUNTIFS($A$2:$A$1001,A4,$B$2:$B$1001,B4)>1,"⚠ Référence en double","✔ OK"))))
L5: =IF(AND(ISNUMBER(J5),ISNUMBER(K5),N(J5)>0),1-K5/J5,"") | U5: =IF((LEN(A5)+LEN(B5)+LEN(C5)+LEN(D5)+LEN(E5)+LEN(F5)+LEN(G5)+LEN(H5)+LEN(I5)+LEN(J5)+LEN(K5)+LEN(M5)+LEN(N5)+LEN(O5)+LEN(P5)+LEN(Q5)+LEN(R5)+LEN(S5)+LEN(T5))=0,"",IF(OR(A5="",B5="",C5="",D5="",E5="",J5="",K5="",N5=""),"⚠ Champ obligatoire manquant",IF(AND(ISNUMBER(K5),ISNUMBER(J5),N(K5)>N(J5)),"⚠ Prix Autopiec > prix public",IF(COUNTIFS($A$2:$A$1001,A5,$B$2:$B$1001,B5)>1,"⚠ Référence en double","✔ OK"))))
L6: =IF(AND(ISNUMBER(J6),ISNUMBER(K6),N(J6)>0),1-K6/J6,"") | U6: =IF((LEN(A6)+LEN(B6)+LEN(C6)+LEN(D6)+LEN(E6)+LEN(F6)+LEN(G6)+LEN(H6)+LEN(I6)+LEN(J6)+LEN(K6)+LEN(M6)+LEN(N6)+LEN(O6)+LEN(P6)+LEN(Q6)+LEN(R6)+LEN(S6)+LEN(T6))=0,"",IF(OR(A6="",B6="",C6="",D6="",E6="",J6="",K6="",N6=""),"⚠ Champ obligatoire manquant",IF(AND(ISNUMBER(K6),ISNUMBER(J6),N(K6)>N(J6)),"⚠ Prix Autopiec > prix public",IF(COUNTIFS($A$2:$A$1001,A6,$B$2:$B$1001,B6)>1,"⚠ Référence en double","✔ OK"))))
L7: =IF(AND(ISNUMBER(J7),ISNUMBER(K7),N(J7)>0),1-K7/J7,"") | U7: =IF((LEN(A7)+LEN(B7)+LEN(C7)+LEN(D7)+LEN(E7)+LEN(F7)+LEN(G7)+LEN(H7)+LEN(I7)+LEN(J7)+LEN(K7)+LEN(M7)+LEN(N7)+LEN(O7)+LEN(P7)+LEN(Q7)+LEN(R7)+LEN(S7)+LEN(T7))=0,"",IF(OR(A7="",B7="",C7="",D7="",E7="",J7="",K7="",N7=""),"⚠ Champ obligatoire manquant",IF(AND(ISNUMBER(K7),ISNUMBER(J7),N(K7)>N(J7)),"⚠ Prix Autopiec > prix public",IF(COUNTIFS($A$2:$A$1001,A7,$B$2:$B$1001,B7)>1,"⚠ Référence en double","✔ OK"))))
L8: =IF(AND(ISNUMBER(J8),ISNUMBER(K8),N(J8)>0),1-K8/J8,"") | U8: =IF((LEN(A8)+LEN(B8)+LEN(C8)+LEN(D8)+LEN(E8)+LEN(F8)+LEN(G8)+LEN(H8)+LEN(I8)+LEN(J8)+LEN(K8)+LEN(M8)+LEN(N8)+LEN(O8)+LEN(P8)+LEN(Q8)+LEN(R8)+LEN(S8)+LEN(T8))=0,"",IF(OR(A8="",B8="",C8="",D8="",E8="",J8="",K8="",N8=""),"⚠ Champ obligatoire manquant",IF(AND(ISNUMBER(K8),ISNUMBER(J8),N(K8)>N(J8)),"⚠ Prix Autopiec > prix public",IF(COUNTIFS($A$2:$A$1001,A8,$B$2:$B$1001,B8)>1,"⚠ Référence en double","✔ OK"))))
L9: =IF(AND(ISNUMBER(J9),ISNUMBER(K9),N(J9)>0),1-K9/J9,"") | U9: =IF((LEN(A9)+LEN(B9)+LEN(C9)+LEN(D9)+LEN(E9)+LEN(F9)+LEN(G9)+LEN(H9)+LEN(I9)+LEN(J9)+LEN(K9)+LEN(M9)+LEN(N9)+LEN(O9)+LEN(P9)+LEN(Q9)+LEN(R9)+LEN(S9)+LEN(T9))=0,"",IF(OR(A9="",B9="",C9="",D9="",E9="",J9="",K9="",N9=""),"⚠ Champ obligatoire manquant",IF(AND(ISNUMBER(K9),ISNUMBER(J9),N(K9)>N(J9)),"⚠ Prix Autopiec > prix public",IF(COUNTIFS($A$2:$A$1001,A9,$B$2:$B$1001,B9)>1,"⚠ Référence en double","✔ OK"))))
L10: =IF(AND(ISNUMBER(J10),ISNUMBER(K10),N(J10)>0),1-K10/J10,"") | U10: =IF((LEN(A10)+LEN(B10)+LEN(C10)+LEN(D10)+LEN(E10)+LEN(F10)+LEN(G10)+LEN(H10)+LEN(I10)+LEN(J10)+LEN(K10)+LEN(M10)+LEN(N10)+LEN(O10)+LEN(P10)+LEN(Q10)+LEN(R10)+LEN(S10)+LEN(T10))=0,"",IF(OR(A10="",B10="",C10="",D10="",E10="",J10="",K10="",N10=""),"⚠ Champ obligatoire manquant",IF(AND(ISNUMBER(K10),ISNUMBER(J10),N(K10)>N(J10)),"⚠ Prix Autopiec > prix public",IF(COUNTIFS($A$2:$A$1001,A10,$B$2:$B$1001,B10)>1,"⚠ Référence en double","✔ OK"))))
L11: =IF(AND(ISNUMBER(J11),ISNUMBER(K11),N(J11)>0),1-K11/J11,"") | U11: =IF((LEN(A11)+LEN(B11)+LEN(C11)+LEN(D11)+LEN(E11)+LEN(F11)+LEN(G11)+LEN(H11)+LEN(I11)+LEN(J11)+LEN(K11)+LEN(M11)+LEN(N11)+LEN(O11)+LEN(P11)+LEN(Q11)+LEN(R11)+LEN(S11)+LEN(T11))=0,"",IF(OR(A11="",B11="",C11="",D11="",E11="",J11="",K11="",N11=""),"⚠ Champ obligatoire manquant",IF(AND(ISNUMBER(K11),ISNUMBER(J11),N(K11)>N(J11)),"⚠ Prix Autopiec > prix public",IF(COUNTIFS($A$2:$A$1001,A11,$B$2:$B$1001,B11)>1,"⚠ Référence en double","✔ OK"))))
L12: =IF(AND(ISNUMBER(J12),ISNUMBER(K12),N(J12)>0),1-K12/J12,"") | U12: =IF((LEN(A12)+LEN(B12)+LEN(C12)+LEN(D12)+LEN(E12)+LEN(F12)+LEN(G12)+LEN(H12)+LEN(I12)+LEN(J12)+LEN(K12)+LEN(M12)+LEN(N12)+LEN(O12)+LEN(P12)+LEN(Q12)+LEN(R12)+LEN(S12)+LEN(T12))=0,"",IF(OR(A12="",B12="",C12="",D12="",E12="",J12="",K12="",N12=""),"⚠ Champ obligatoire manquant",IF(AND(ISNUMBER(K12),ISNUMBER(J12),N(K12)>N(J12)),"⚠ Prix Autopiec > prix public",IF(COUNTIFS($A$2:$A$1001,A12,$B$2:$B$1001,B12)>1,"⚠ Référence en double","✔ OK"))))
L13: =IF(AND(ISNUMBER(J13),ISNUMBER(K13),N(J13)>0),1-K13/J13,"") | U13: =IF((LEN(A13)+LEN(B13)+LEN(C13)+LEN(D13)+LEN(E13)+LEN(F13)+LEN(G13)+LEN(H13)+LEN(I13)+LEN(J13)+LEN(K13)+LEN(M13)+LEN(N13)+LEN(O13)+LEN(P13)+LEN(Q13)+LEN(R13)+LEN(S13)+LEN(T13))=0,"",IF(OR(A13="",B13="",C13="",D13="",E13="",J13="",K13="",N13=""),"⚠ Champ obligatoire manquant",IF(AND(ISNUMBER(K13),ISNUMBER(J13),N(K13)>N(J13)),"⚠ Prix Autopiec > prix public",IF(COUNTIFS($A$2:$A$1001,A13,$B$2:$B$1001,B13)>1,"⚠ Référence en double","✔ OK"))))
... L1001: =IF(AND(ISNUMBER(J1001),ISNUMBER(K1001),N(J1001)>0),1-K1001/J1001,"") | U1001: =IF((LEN(A1001)+LEN(B1001)+LEN(C1001)+LEN(D1001)+LEN(E1001)+LEN(F1001)+LEN(G1001)+LEN(H1001)+LEN(I1001)+LEN(J1001)+LEN(K1001)+LEN(M1001)+LEN(N1001)+LEN(O1001)+LEN(P1001)+LEN(Q1001)+LEN(R1001)+LEN(S1001)+LEN(T1001))=0,"",IF(OR(A1001="",B1001="",C1001="",D1001="",E1001="",J1001="",K1001="",N1001=""),"⚠ Champ obligatoire manquant",IF(AND(ISNUMBER(K1001),ISNUMBER(J1001),N(K1001)>N(J1001)),"⚠ Prix Autopiec > prix public",IF(COUNTIFS($A$2:$A$1001,A1001,$B$2:$B$1001,B1001)>1,"⚠ Référence en double","✔ OK"))))

Sheet Listes
A1: Marques | B1: Catégories | C1: États | D1: TVA | E1: Unités | G1: Listes de référence — vous pouvez compléter la colonne Marques si besoin.
A2: Bosch | B2: Freinage | C2: Neuf | D2: 0.2 | E2: Pièce
A3: Valeo | B3: Filtration | C3: Reconditionné / Échange standard | D3: 0.1 | E3: Paire
A4: Brembo | B4: Moteur | C4: Occasion | D4: 0.055 | E4: Kit
A5: TRW | B5: Distribution | D5: 0 | E5: Jeu
A6: Febi Bilstein | B6: Embrayage | E6: Litre
A7: SKF | B7: Suspension / Amortisseurs | E7: Mètre
A8: Gates | B8: Direction
A9: Mann-Filter | B9: Transmission
A10: Mahle | B10: Échappement
A11: NGK | B11: Refroidissement
A12: Denso | B12: Électricité / Allumage
A13: Sachs | B13: Éclairage
A14: Monroe | B14: Carrosserie
A15: LuK | B15: Climatisation
A16: Continental | B16: Huiles & Liquides
A17: Hella | B17: Pneumatiques
A18: Delphi | B18: Accessoires
A19: Ferodo | B19: Autre
A20: Purflux
A21: Autre (préciser en commentaire)
